debug_this/__init__.py
debug_this/py.typed
debug_this-1.0.2.dist-info/LICENSE.md
debug_this-1.0.2.dist-info/METADATA
debug_this-1.0.2.dist-info/WHEEL
debug_this-1.0.2.dist-info/top_level.txt
debug_this-1.0.2.dist-info/RECORD
