Metadata-Version: 2.1
Name: debug-this
Version: 1.0.2
Summary: Python debug logging helpers
Home-page: https://github.com/jmlemetayer/python-debug-this
Author: Jean-Marie Lemetayer
Author-email: jeanmarie.lemetayer@gmail.com
License: MIT
Project-URL: Documentation, https://python-debug-this.readthedocs.io
Project-URL: Issues, https://github.com/jmlemetayer/python-debug-this/issues
Classifier: License :: OSI Approved :: MIT License
Classifier: Programming Language :: Python :: 3
Classifier: Programming Language :: Python :: 3 :: Only
Classifier: Programming Language :: Python :: 3.8
Classifier: Programming Language :: Python :: 3.9
Classifier: Programming Language :: Python :: 3.10
Requires-Python: >=3.8
License-File: LICENSE.md
Provides-Extra: tests
Requires-Dist: pytest (>=7.1) ; extra == 'tests'
